eigenpairflow/__init__.py
eigenpairflow/correction.py
eigenpairflow/graph.py
eigenpairflow/magnitude.py
eigenpairflow/ode.py
eigenpairflow/tracking.py
eigenpairflow/types.py
eigenpairflow/visualization.py
eigenpairflow-0.2.0.dist-info/LICENSE
eigenpairflow-0.2.0.dist-info/METADATA
eigenpairflow-0.2.0.dist-info/WHEEL
eigenpairflow-0.2.0.dist-info/RECORD
