Metadata-Version: 2.3
Name: eigenpairflow
Version: 0.2.0
Summary: Continuous and stable tracking of eigendecomposition for parameter-dependent matrices
License: MIT
Keywords: eigendecomposition,eigenvalue,eigenvector,tracking,numerical-methods
Author: Tomoki Uda
Author-email: tomoki.uda@gmail.com
Requires-Python: >=3.9
Classifier: License :: OSI Approved :: MIT License
Classifier: Programming Language :: Python :: 3
Classifier: Programming Language :: Python :: 3.9
Classifier: Programming Language :: Python :: 3.10
Classifier: Programming Language :: Python :: 3.11
Classifier: Programming Language :: Python :: 3.12
Classifier: Operating System :: OS Independent
Classifier: Topic :: Scientific/Engineering
Classifier: Intended Audience :: Science/Research
Requires-Dist: joblib (>=1.3.2)
Requires-Dist: matplotlib (>=3.4.0)
Requires-Dist: networkx (>=2.6.0)
Requires-Dist: numpy (>=1.21.0)
Requires-Dist: scipy (>=1.7.0)
Project-URL: Homepage, https://github.com/t-uda/EigenpairFlow
Project-URL: Repository, https://github.com/t-uda/EigenpairFlow
